[
  {
    "name": "#Ευαγγελατε_Γαμιεσαι",
    "query": "#Ευαγγελατε_Γαμιεσαι",
    "rank": 1,
    "tweet_count": "4,914 Tweets"
  },
  {
    "name": "#τζοκοβιτς",
    "query": "#τζοκοβιτς",
    "rank": 2,
    "tweet_count": "5,886 Tweets"
  },
  {
    "name": "#survivorGR",
    "query": "#survivorGR",
    "rank": 3,
    "tweet_count": "2,211 Tweets"
  },
  {
    "name": "#Θεοφανεια",
    "query": "#Θεοφανεια",
    "rank": 4,
    "tweet_count": "2,939 Tweets"
  },
  {
    "name": "Γιαννη",
    "query": "Γιαννη",
    "rank": 5,
    "tweet_count": "2,173 Tweets"
  },
  {
    "name": "#mousikokouti",
    "query": "#mousikokouti",
    "rank": 6,
    "tweet_count": null
  },
  {
    "name": "Καζακσταν",
    "query": "Καζακσταν",
    "rank": 7,
    "tweet_count": "5,033 Tweets"
  },
  {
    "name": "Ιωαννα",
    "query": "Ιωαννα",
    "rank": 8,
    "tweet_count": null
  },
  {
    "name": "Πολυχρονος",
    "query": "Πολυχρονος",
    "rank": 9,
    "tweet_count": null
  },
  {
    "name": "Αυστραλια",
    "query": "Αυστραλια",
    "rank": 10,
    "tweet_count": "2,724 Tweets"
  },
  {
    "name": "Καλημερα Κατια",
    "query": "\"Καλημερα Κατια\"",
    "rank": 11,
    "tweet_count": null
  },
  {
    "name": "Αη Στρατη",
    "query": "\"Αη Στρατη\"",
    "rank": 12,
    "tweet_count": "5,003 Tweets"
  },
  {
    "name": "Ιανουαριο",
    "query": "Ιανουαριο",
    "rank": 13,
    "tweet_count": null
  },
  {
    "name": "φωτιση",
    "query": "φωτιση",
    "rank": 14,
    "tweet_count": "4,396 Tweets"
  },
  {
    "name": "Μυριελλα",
    "query": "Μυριελλα",
    "rank": 15,
    "tweet_count": null
  },
  {
    "name": "Χρονια Πολλα",
    "query": "\"Χρονια Πολλα\"",
    "rank": 16,
    "tweet_count": "14.1K Tweets"
  },
  {
    "name": "βαλαντη",
    "query": "βαλαντη",
    "rank": 17,
    "tweet_count": null
  },
  {
    "name": "Ευχαριστω",
    "query": "Ευχαριστω",
    "rank": 18,
    "tweet_count": "6,570 Tweets"
  },
  {
    "name": "Με 10",
    "query": "\"Με 10\"",
    "rank": 19,
    "tweet_count": "2,114 Tweets"
  },
  {
    "name": "Australia",
    "query": "Australia",
    "rank": 20,
    "tweet_count": "419K Tweets"
  }
]
