[
  {
    "name": "Happy New Year",
    "query": "\"Happy New Year\"",
    "rank": 1,
    "tweet_count": "147K Tweets"
  },
  {
    "name": "Burger King",
    "query": "\"Burger King\"",
    "rank": 2,
    "tweet_count": "27.5K Tweets"
  },
  {
    "name": "The CDC",
    "query": "\"The CDC\"",
    "rank": 3,
    "tweet_count": "324K Tweets"
  },
  {
    "name": "Air Force",
    "query": "\"Air Force\"",
    "rank": 4,
    "tweet_count": "9,096 Tweets"
  },
  {
    "name": "#tuesdaymotivations",
    "query": "#tuesdaymotivations",
    "rank": 5,
    "tweet_count": "18.6K Tweets"
  },
  {
    "name": "#BadNamesForCovidVariants",
    "query": "#BadNamesForCovidVariants",
    "rank": 6,
    "tweet_count": "1,087 Tweets"
  },
  {
    "name": "Southampton",
    "query": "Southampton",
    "rank": 7,
    "tweet_count": "21.9K Tweets"
  },
  {
    "name": "#BloomingSANAday",
    "query": "#BloomingSANAday",
    "rank": 8,
    "tweet_count": "172K Tweets"
  },
  {
    "name": "Navarro",
    "query": "Navarro",
    "rank": 9,
    "tweet_count": "62.7K Tweets"
  },
  {
    "name": "Lindsay Ellis",
    "query": "\"Lindsay Ellis\"",
    "rank": 10,
    "tweet_count": "11.2K Tweets"
  },
  {
    "name": "Insigne",
    "query": "Insigne",
    "rank": 11,
    "tweet_count": "9,291 Tweets"
  },
  {
    "name": "#snailgang",
    "query": "#snailgang",
    "rank": 12,
    "tweet_count": null
  },
  {
    "name": "Delta CEO",
    "query": "\"Delta CEO\"",
    "rank": 13,
    "tweet_count": "26.8K Tweets"
  },
  {
    "name": "Stetson",
    "query": "Stetson",
    "rank": 14,
    "tweet_count": "1,193 Tweets"
  },
  {
    "name": "Dabo",
    "query": "Dabo",
    "rank": 15,
    "tweet_count": "2,348 Tweets"
  },
  {
    "name": "Harry Kane",
    "query": "\"Harry Kane\"",
    "rank": 16,
    "tweet_count": "4,067 Tweets"
  },
  {
    "name": "Taco Tuesday",
    "query": "\"Taco Tuesday\"",
    "rank": 17,
    "tweet_count": "1,872 Tweets"
  },
  {
    "name": "Watford",
    "query": "Watford",
    "rank": 18,
    "tweet_count": "16.3K Tweets"
  },
  {
    "name": "Dax Hill",
    "query": "\"Dax Hill\"",
    "rank": 19,
    "tweet_count": null
  }
]
