[
  {
    "name": "Covid",
    "query": "Covid",
    "rank": 1,
    "tweet_count": "1.13M Tweets"
  },
  {
    "name": "Stockport",
    "query": "Stockport",
    "rank": 2,
    "tweet_count": "4,452 Tweets"
  },
  {
    "name": "Young Dolph",
    "query": "\"Young Dolph\"",
    "rank": 3,
    "tweet_count": "441K Tweets"
  },
  {
    "name": "#WhoWantsToBeAMillionaire",
    "query": "#WhoWantsToBeAMillionaire",
    "rank": 4,
    "tweet_count": "1,142 Tweets"
  },
  {
    "name": "Bradley Brooks",
    "query": "\"Bradley Brooks\"",
    "rank": 5,
    "tweet_count": null
  },
  {
    "name": "#Corrie",
    "query": "#Corrie",
    "rank": 6,
    "tweet_count": "1,426 Tweets"
  },
  {
    "name": "#UncannyListenAlong",
    "query": "#UncannyListenAlong",
    "rank": 7,
    "tweet_count": null
  },
  {
    "name": "TWO Return Flights to Hawaii",
    "query": "\"TWO Return Flights to Hawaii\"",
    "rank": 8,
    "tweet_count": null
  },
  {
    "name": "Davido",
    "query": "Davido",
    "rank": 9,
    "tweet_count": "400K Tweets"
  },
  {
    "name": "#Shetland",
    "query": "#Shetland",
    "rank": 10,
    "tweet_count": null
  },
  {
    "name": "#STOBOL",
    "query": "#STOBOL",
    "rank": 11,
    "tweet_count": null
  },
  {
    "name": "David Lacey",
    "query": "\"David Lacey\"",
    "rank": 12,
    "tweet_count": null
  },
  {
    "name": "Ebony",
    "query": "Ebony",
    "rank": 13,
    "tweet_count": "10.8K Tweets"
  },
  {
    "name": "Psquare",
    "query": "Psquare",
    "rank": 14,
    "tweet_count": "4,835 Tweets"
  },
  {
    "name": "Shamima Begum",
    "query": "\"Shamima Begum\"",
    "rank": 15,
    "tweet_count": "3,779 Tweets"
  },
  {
    "name": "Kachunga",
    "query": "Kachunga",
    "rank": 16,
    "tweet_count": null
  },
  {
    "name": "Quigley",
    "query": "Quigley",
    "rank": 17,
    "tweet_count": "1,942 Tweets"
  },
  {
    "name": "Nadine",
    "query": "Nadine",
    "rank": 18,
    "tweet_count": "12.9K Tweets"
  },
  {
    "name": "Rachel Johnson",
    "query": "\"Rachel Johnson\"",
    "rank": 19,
    "tweet_count": "2,700 Tweets"
  },
  {
    "name": "Evatt",
    "query": "Evatt",
    "rank": 20,
    "tweet_count": null
  }
]
