[
  {
    "name": "#باز_يجمعنا",
    "query": "#باز_يجمعنا",
    "rank": 1,
    "tweet_count": null
  },
  {
    "name": "#WelcomeHomeSuho",
    "query": "#WelcomeHomeSuho",
    "rank": 2,
    "tweet_count": "416K Tweets"
  },
  {
    "name": "الاهلي",
    "query": "الاهلي",
    "rank": 3,
    "tweet_count": "424K Tweets"
  },
  {
    "name": "أوكرانيا",
    "query": "أوكرانيا",
    "rank": 4,
    "tweet_count": "115K Tweets"
  },
  {
    "name": "#ساعه_استجابه",
    "query": "#ساعه_استجابه",
    "rank": 5,
    "tweet_count": "31.3K Tweets"
  },
  {
    "name": "#جمعه_مباركه",
    "query": "#جمعه_مباركه",
    "rank": 6,
    "tweet_count": "10.4K Tweets"
  },
  {
    "name": "#البزنس69",
    "query": "#البزنس69",
    "rank": 7,
    "tweet_count": "59.3K Tweets"
  },
  {
    "name": "Ukraine",
    "query": "Ukraine",
    "rank": 8,
    "tweet_count": "657K Tweets"
  },
  {
    "name": "تشيلسي",
    "query": "تشيلسي",
    "rank": 9,
    "tweet_count": "51K Tweets"
  },
  {
    "name": "محمد",
    "query": "محمد",
    "rank": 10,
    "tweet_count": "296K Tweets"
  },
  {
    "name": "Jungkook",
    "query": "Jungkook",
    "rank": 11,
    "tweet_count": "1.26M Tweets"
  },
  {
    "name": "امريكا",
    "query": "امريكا",
    "rank": 12,
    "tweet_count": "73.8K Tweets"
  },
  {
    "name": "الذريه الصالحه",
    "query": "\"الذريه الصالحه\"",
    "rank": 13,
    "tweet_count": null
  },
  {
    "name": "علي الجميع",
    "query": "\"علي الجميع\"",
    "rank": 14,
    "tweet_count": "9,995 Tweets"
  },
  {
    "name": "الإمارات",
    "query": "الإمارات",
    "rank": 15,
    "tweet_count": "34.5K Tweets"
  },
  {
    "name": "yunho",
    "query": "yunho",
    "rank": 16,
    "tweet_count": "69.2K Tweets"
  },
  {
    "name": "بريطانيا",
    "query": "بريطانيا",
    "rank": 17,
    "tweet_count": "9,373 Tweets"
  },
  {
    "name": "صلاح",
    "query": "صلاح",
    "rank": 18,
    "tweet_count": "14.1K Tweets"
  },
  {
    "name": "رونالدو",
    "query": "رونالدو",
    "rank": 19,
    "tweet_count": "8,438 Tweets"
  },
  {
    "name": "تويتر",
    "query": "تويتر",
    "rank": 20,
    "tweet_count": "104K Tweets"
  }
]
