[
  {
    "name": "#thevoicekids",
    "query": "#thevoicekids",
    "rank": 1,
    "tweet_count": "10.8K Tweets"
  },
  {
    "name": "#marvelezpolsatem",
    "query": "#marvelezpolsatem",
    "rank": 2,
    "tweet_count": "1,929 Tweets"
  },
  {
    "name": "#KSW67",
    "query": "#KSW67",
    "rank": 3,
    "tweet_count": "1,174 Tweets"
  },
  {
    "name": "#klimoff",
    "query": "#klimoff",
    "rank": 4,
    "tweet_count": null
  },
  {
    "name": "Olejnik",
    "query": "Olejnik",
    "rank": 5,
    "tweet_count": "3,707 Tweets"
  },
  {
    "name": "Część",
    "query": "Część",
    "rank": 6,
    "tweet_count": "9,812 Tweets"
  },
  {
    "name": "Kijów",
    "query": "Kijów",
    "rank": 7,
    "tweet_count": "27.7K Tweets"
  },
  {
    "name": "Kadyrowa",
    "query": "Kadyrowa",
    "rank": 8,
    "tweet_count": "5,012 Tweets"
  },
  {
    "name": "Braun",
    "query": "Braun",
    "rank": 9,
    "tweet_count": "8,992 Tweets"
  },
  {
    "name": "#porebqaspaces",
    "query": "#porebqaspaces",
    "rank": 10,
    "tweet_count": null
  },
  {
    "name": "Czeczeni",
    "query": "Czeczeni",
    "rank": 11,
    "tweet_count": "2,901 Tweets"
  },
  {
    "name": "Dawid",
    "query": "Dawid",
    "rank": 12,
    "tweet_count": "4,607 Tweets"
  },
  {
    "name": "Czeczenów",
    "query": "Czeczenów",
    "rank": 13,
    "tweet_count": "2,852 Tweets"
  },
  {
    "name": "trzymajcie",
    "query": "trzymajcie",
    "rank": 14,
    "tweet_count": "1,616 Tweets"
  },
  {
    "name": "JAZDA Z KURWAMI",
    "query": "\"JAZDA Z KURWAMI\"",
    "rank": 15,
    "tweet_count": "6,662 Tweets"
  },
  {
    "name": "#UkraineRussiaWar",
    "query": "#UkraineRussiaWar",
    "rank": 16,
    "tweet_count": "179K Tweets"
  },
  {
    "name": "#PIAGÓR",
    "query": "#PIAGÓR",
    "rank": 17,
    "tweet_count": null
  },
  {
    "name": "#WojnaWUkrainie",
    "query": "#WojnaWUkrainie",
    "rank": 18,
    "tweet_count": null
  },
  {
    "name": "#Anonymous",
    "query": "#Anonymous",
    "rank": 19,
    "tweet_count": "236K Tweets"
  },
  {
    "name": "#FckPutin",
    "query": "#FckPutin",
    "rank": 20,
    "tweet_count": "44.2K Tweets"
  }
]
