[
  {
    "name": "Mikael",
    "query": "Mikael",
    "rank": 1,
    "tweet_count": "16.1K Tweets"
  },
  {
    "name": "Rodallega",
    "query": "Rodallega",
    "rank": 2,
    "tweet_count": "1,123 Tweets"
  },
  {
    "name": "Cirino",
    "query": "Cirino",
    "rank": 3,
    "tweet_count": null
  },
  {
    "name": "jadson",
    "query": "jadson",
    "rank": 4,
    "tweet_count": null
  },
  {
    "name": "em busca do penta",
    "query": "\"em busca do penta\"",
    "rank": 5,
    "tweet_count": "7,904 Tweets"
  },
  {
    "name": "jacuipense",
    "query": "jacuipense",
    "rank": 6,
    "tweet_count": null
  },
  {
    "name": "marco ant么nio",
    "query": "\"marco ant么nio\"",
    "rank": 7,
    "tweet_count": "1,695 Tweets"
  },
  {
    "name": "campinense",
    "query": "campinense",
    "rank": 8,
    "tweet_count": "1,065 Tweets"
  },
  {
    "name": "Vit贸ria",
    "query": "Vit贸ria",
    "rank": 9,
    "tweet_count": "33.9K Tweets"
  },
  {
    "name": "#AustralianOpenNaESPN",
    "query": "#AustralianOpenNaESPN",
    "rank": 10,
    "tweet_count": "2,954 Tweets"
  },
  {
    "name": "Danilina",
    "query": "Danilina",
    "rank": 11,
    "tweet_count": "2,213 Tweets"
  },
  {
    "name": "#antivslarriesabadou",
    "query": "#antivslarriesabadou",
    "rank": 12,
    "tweet_count": "6,941 Tweets"
  },
  {
    "name": "#olavooo",
    "query": "#olavooo",
    "rank": 13,
    "tweet_count": "1,646 Tweets"
  },
  {
    "name": "#ForaBozo",
    "query": "#ForaBozo",
    "rank": 14,
    "tweet_count": "2,151 Tweets"
  },
  {
    "name": "#BolsonaroGenocida",
    "query": "#BolsonaroGenocida",
    "rank": 15,
    "tweet_count": "3,062 Tweets"
  },
  {
    "name": "28 X",
    "query": "\"28 X\"",
    "rank": 16,
    "tweet_count": "8,968 Tweets"
  },
  {
    "name": "Bia Haddad",
    "query": "\"Bia Haddad\"",
    "rank": 17,
    "tweet_count": "1,081 Tweets"
  },
  {
    "name": "Michael Jackson",
    "query": "\"Michael Jackson\"",
    "rank": 18,
    "tweet_count": "32.5K Tweets"
  }
]
