[
  {
    "name": "#olyast",
    "query": "#olyast",
    "rank": 1,
    "tweet_count": null
  },
  {
    "name": "#aekpaok",
    "query": "#aekpaok",
    "rank": 2,
    "tweet_count": null
  },
  {
    "name": "#MegaLiveNews",
    "query": "#MegaLiveNews",
    "rank": 3,
    "tweet_count": "1,347 Tweets"
  },
  {
    "name": "#OlympiacosFC",
    "query": "#OlympiacosFC",
    "rank": 4,
    "tweet_count": null
  },
  {
    "name": "#KatiXanapsinetai",
    "query": "#KatiXanapsinetai",
    "rank": 5,
    "tweet_count": null
  },
  {
    "name": "Ευαγγελατος",
    "query": "Ευαγγελατος",
    "rank": 6,
    "tweet_count": null
  },
  {
    "name": "δαντη",
    "query": "δαντη",
    "rank": 7,
    "tweet_count": null
  },
  {
    "name": "καλοταξιδο",
    "query": "καλοταξιδο",
    "rank": 8,
    "tweet_count": null
  },
  {
    "name": "Τσαικοφσκι",
    "query": "Τσαικοφσκι",
    "rank": 9,
    "tweet_count": "1,826 Tweets"
  },
  {
    "name": "γρηγορης",
    "query": "γρηγορης",
    "rank": 10,
    "tweet_count": null
  },
  {
    "name": "ντοστογιεφσκι",
    "query": "ντοστογιεφσκι",
    "rank": 11,
    "tweet_count": "1,386 Tweets"
  },
  {
    "name": "χριστοφορος",
    "query": "χριστοφορος",
    "rank": 12,
    "tweet_count": null
  },
  {
    "name": "μερα 16",
    "query": "\"μερα 16\"",
    "rank": 13,
    "tweet_count": null
  },
  {
    "name": "ευαγγελου",
    "query": "ευαγγελου",
    "rank": 14,
    "tweet_count": null
  },
  {
    "name": "Λιατσος",
    "query": "Λιατσος",
    "rank": 15,
    "tweet_count": null
  },
  {
    "name": "Ουκρανιας",
    "query": "Ουκρανιας",
    "rank": 16,
    "tweet_count": "6,302 Tweets"
  },
  {
    "name": "νικηφορος",
    "query": "νικηφορος",
    "rank": 17,
    "tweet_count": null
  },
  {
    "name": "ζαλγκιρις",
    "query": "ζαλγκιρις",
    "rank": 18,
    "tweet_count": null
  },
  {
    "name": "Τεταρτης",
    "query": "Τεταρτης",
    "rank": 19,
    "tweet_count": null
  },
  {
    "name": "Pfizer",
    "query": "Pfizer",
    "rank": 20,
    "tweet_count": "315K Tweets"
  }
]
