[
  {
    "name": "#CrisLu3D",
    "query": "#CrisLu3D",
    "rank": 1,
    "tweet_count": "53.1K Tweets"
  },
  {
    "name": "#Secret4D",
    "query": "#Secret4D",
    "rank": 2,
    "tweet_count": "2,854 Tweets"
  },
  {
    "name": "#TCMS5",
    "query": "#TCMS5",
    "rank": 3,
    "tweet_count": "17.6K Tweets"
  },
  {
    "name": "#LCDP5",
    "query": "#LCDP5",
    "rank": 4,
    "tweet_count": "120K Tweets"
  },
  {
    "name": "Luca",
    "query": "Luca",
    "rank": 5,
    "tweet_count": "66.4K Tweets"
  },
  {
    "name": "#Adara4D",
    "query": "#Adara4D",
    "rank": 6,
    "tweet_count": null
  },
  {
    "name": "Agoney",
    "query": "Agoney",
    "rank": 7,
    "tweet_count": "14.2K Tweets"
  },
  {
    "name": "Alicia Sierra",
    "query": "\"Alicia Sierra\"",
    "rank": 8,
    "tweet_count": "8,355 Tweets"
  },
  {
    "name": "Huesca",
    "query": "Huesca",
    "rank": 9,
    "tweet_count": "2,319 Tweets"
  },
  {
    "name": "5sos",
    "query": "5sos",
    "rank": 10,
    "tweet_count": "275K Tweets"
  },
  {
    "name": "Denver",
    "query": "Denver",
    "rank": 11,
    "tweet_count": "30.2K Tweets"
  },
  {
    "name": "Tokio",
    "query": "Tokio",
    "rank": 12,
    "tweet_count": "44.8K Tweets"
  },
  {
    "name": "Berlín",
    "query": "Berlín",
    "rank": 13,
    "tweet_count": "52.6K Tweets"
  },
  {
    "name": "#LaCasaDePapael5",
    "query": "#LaCasaDePapael5",
    "rank": 14,
    "tweet_count": "16.4K Tweets"
  },
  {
    "name": "#Cris3D",
    "query": "#Cris3D",
    "rank": 15,
    "tweet_count": null
  },
  {
    "name": "#MareaEsUnion",
    "query": "#MareaEsUnion",
    "rank": 16,
    "tweet_count": "6,420 Tweets"
  },
  {
    "name": "#yoconAlvise",
    "query": "#yoconAlvise",
    "rank": 17,
    "tweet_count": "4,235 Tweets"
  },
  {
    "name": "#HappyBirthdayJin",
    "query": "#HappyBirthdayJin",
    "rank": 18,
    "tweet_count": "1.12M Tweets"
  }
]
