[
  {
    "name": "Mushroom",
    "query": "Mushroom",
    "rank": 1,
    "tweet_count": "15.2K Tweets"
  },
  {
    "name": "#nrkmgp",
    "query": "#nrkmgp",
    "rank": 2,
    "tweet_count": "2,664 Tweets"
  },
  {
    "name": "Michelle Keegan",
    "query": "\"Michelle Keegan\"",
    "rank": 3,
    "tweet_count": null
  },
  {
    "name": "Falcons",
    "query": "Falcons",
    "rank": 4,
    "tweet_count": "8,958 Tweets"
  },
  {
    "name": "#SaturdayNight",
    "query": "#SaturdayNight",
    "rank": 5,
    "tweet_count": "1,033 Tweets"
  },
  {
    "name": "Sheridan Smith",
    "query": "\"Sheridan Smith\"",
    "rank": 6,
    "tweet_count": null
  },
  {
    "name": "#AllOfUsAreDead",
    "query": "#AllOfUsAreDead",
    "rank": 7,
    "tweet_count": "205K Tweets"
  },
  {
    "name": "#newvglo",
    "query": "#newvglo",
    "rank": 8,
    "tweet_count": null
  },
  {
    "name": "Bolton",
    "query": "Bolton",
    "rank": 9,
    "tweet_count": "20.4K Tweets"
  },
  {
    "name": "Derek",
    "query": "Derek",
    "rank": 10,
    "tweet_count": "14.9K Tweets"
  },
  {
    "name": "MATCH REPORT",
    "query": "\"MATCH REPORT\"",
    "rank": 11,
    "tweet_count": "1,763 Tweets"
  },
  {
    "name": "Phil Jones",
    "query": "\"Phil Jones\"",
    "rank": 12,
    "tweet_count": "11.7K Tweets"
  },
  {
    "name": "Norwood",
    "query": "Norwood",
    "rank": 13,
    "tweet_count": "1,162 Tweets"
  },
  {
    "name": "Millwall",
    "query": "Millwall",
    "rank": 14,
    "tweet_count": "6,027 Tweets"
  },
  {
    "name": "Lewes",
    "query": "Lewes",
    "rank": 15,
    "tweet_count": "1,847 Tweets"
  },
  {
    "name": "Lesnar",
    "query": "Lesnar",
    "rank": 16,
    "tweet_count": "13.3K Tweets"
  },
  {
    "name": "Botman",
    "query": "Botman",
    "rank": 17,
    "tweet_count": null
  },
  {
    "name": "Brock",
    "query": "Brock",
    "rank": 18,
    "tweet_count": "22.9K Tweets"
  },
  {
    "name": "James Blunt",
    "query": "\"James Blunt\"",
    "rank": 19,
    "tweet_count": "2,601 Tweets"
  }
]
