[
  {
    "name": "#Walls",
    "query": "#Walls",
    "rank": 1,
    "tweet_count": "23.1K Tweets"
  },
  {
    "name": "#LouisTomlinson",
    "query": "#LouisTomlinson",
    "rank": 2,
    "tweet_count": "25.2K Tweets"
  },
  {
    "name": "Milagro Sala",
    "query": "\"Milagro Sala\"",
    "rank": 3,
    "tweet_count": "14.3K Tweets"
  },
  {
    "name": "#ElTopoLeDiceNoAlMonopolio",
    "query": "#ElTopoLeDiceNoAlMonopolio",
    "rank": 4,
    "tweet_count": "1,427 Tweets"
  },
  {
    "name": "Modric",
    "query": "Modric",
    "rank": 5,
    "tweet_count": "30.5K Tweets"
  },
  {
    "name": "Berni",
    "query": "Berni",
    "rank": 6,
    "tweet_count": "24.3K Tweets"
  },
  {
    "name": "Australia",
    "query": "Australia",
    "rank": 7,
    "tweet_count": "468K Tweets"
  },
  {
    "name": "sunmi",
    "query": "sunmi",
    "rank": 8,
    "tweet_count": "22.2K Tweets"
  },
  {
    "name": "#SKZ_EXPO2020Dubai",
    "query": "#SKZ_EXPO2020Dubai",
    "rank": 9,
    "tweet_count": "123K Tweets"
  },
  {
    "name": "#2YearsWithBlackSwan",
    "query": "#2YearsWithBlackSwan",
    "rank": 10,
    "tweet_count": "16.4K Tweets"
  },
  {
    "name": "Evanescence",
    "query": "Evanescence",
    "rank": 11,
    "tweet_count": "2,601 Tweets"
  },
  {
    "name": "Paul Newman",
    "query": "\"Paul Newman\"",
    "rank": 12,
    "tweet_count": null
  },
  {
    "name": "Djokovic",
    "query": "Djokovic",
    "rank": 13,
    "tweet_count": "615K Tweets"
  },
  {
    "name": "Sierra Leona",
    "query": "\"Sierra Leona\"",
    "rank": 14,
    "tweet_count": "1,103 Tweets"
  },
  {
    "name": "Leeds",
    "query": "Leeds",
    "rank": 15,
    "tweet_count": "51.9K Tweets"
  },
  {
    "name": "Chelo",
    "query": "Chelo",
    "rank": 16,
    "tweet_count": "1,694 Tweets"
  },
  {
    "name": "Costa de Marfil",
    "query": "\"Costa de Marfil\"",
    "rank": 17,
    "tweet_count": null
  },
  {
    "name": "Bielsa",
    "query": "Bielsa",
    "rank": 18,
    "tweet_count": "7,699 Tweets"
  },
  {
    "name": "Infobae",
    "query": "Infobae",
    "rank": 19,
    "tweet_count": "32.8K Tweets"
  }
]
