[
  {
    "name": "Agripino Núñez Collado",
    "query": "\"Agripino Núñez Collado\"",
    "rank": 1,
    "tweet_count": "3,271 Tweets"
  },
  {
    "name": "Gigantes del Cibao",
    "query": "\"Gigantes del Cibao\"",
    "rank": 2,
    "tweet_count": "1,548 Tweets"
  },
  {
    "name": "PUCMM",
    "query": "PUCMM",
    "rank": 3,
    "tweet_count": "1,140 Tweets"
  },
  {
    "name": "#leonelquedasolo",
    "query": "#leonelquedasolo",
    "rank": 4,
    "tweet_count": null
  },
  {
    "name": "Siri",
    "query": "Siri",
    "rank": 5,
    "tweet_count": "16.8K Tweets"
  },
  {
    "name": "Campeones",
    "query": "Campeones",
    "rank": 6,
    "tweet_count": "12.2K Tweets"
  },
  {
    "name": "Uber",
    "query": "Uber",
    "rank": 7,
    "tweet_count": "64.7K Tweets"
  },
  {
    "name": "tetelo vargas",
    "query": "\"tetelo vargas\"",
    "rank": 8,
    "tweet_count": null
  },
  {
    "name": "#pldresponda",
    "query": "#pldresponda",
    "rank": 9,
    "tweet_count": null
  },
  {
    "name": "Marcell Ozuna",
    "query": "\"Marcell Ozuna\"",
    "rank": 10,
    "tweet_count": null
  },
  {
    "name": "#UFC270",
    "query": "#UFC270",
    "rank": 11,
    "tweet_count": "363K Tweets"
  },
  {
    "name": "Domínguez Brito",
    "query": "\"Domínguez Brito\"",
    "rank": 12,
    "tweet_count": null
  },
  {
    "name": "Karol G",
    "query": "\"Karol G\"",
    "rank": 13,
    "tweet_count": "1,863 Tweets"
  },
  {
    "name": "#abelpuetopati",
    "query": "#abelpuetopati",
    "rank": 14,
    "tweet_count": null
  },
  {
    "name": "otero",
    "query": "otero",
    "rank": 15,
    "tweet_count": "7,615 Tweets"
  },
  {
    "name": "Faride",
    "query": "Faride",
    "rank": 16,
    "tweet_count": null
  },
  {
    "name": "#virgendelaaltagracia",
    "query": "#virgendelaaltagracia",
    "rank": 17,
    "tweet_count": null
  },
  {
    "name": "Estrellas Orientales",
    "query": "\"Estrellas Orientales\"",
    "rank": 18,
    "tweet_count": null
  },
  {
    "name": "Packers",
    "query": "Packers",
    "rank": 19,
    "tweet_count": "416K Tweets"
  },
  {
    "name": "BTS GOLDEN DISCOGRAPHY",
    "query": "\"BTS GOLDEN DISCOGRAPHY\"",
    "rank": 20,
    "tweet_count": "28.9K Tweets"
  }
]
