[
  {
    "name": "#Amici21",
    "query": "#Amici21",
    "rank": 1,
    "tweet_count": "54.7K Tweets"
  },
  {
    "name": "#VeronaLazio",
    "query": "#VeronaLazio",
    "rank": 2,
    "tweet_count": "1,227 Tweets"
  },
  {
    "name": "Richard Gere",
    "query": "\"Richard Gere\"",
    "rank": 3,
    "tweet_count": "7,133 Tweets"
  },
  {
    "name": "Christian",
    "query": "Christian",
    "rank": 4,
    "tweet_count": "76.9K Tweets"
  },
  {
    "name": "#MotoGP",
    "query": "#MotoGP",
    "rank": 5,
    "tweet_count": "47K Tweets"
  },
  {
    "name": "#FiorentinaCagliari",
    "query": "#FiorentinaCagliari",
    "rank": 6,
    "tweet_count": null
  },
  {
    "name": "Amedeo",
    "query": "Amedeo",
    "rank": 7,
    "tweet_count": "1,687 Tweets"
  },
  {
    "name": "Alex",
    "query": "Alex",
    "rank": 8,
    "tweet_count": "258K Tweets"
  },
  {
    "name": "Sebastian",
    "query": "Sebastian",
    "rank": 9,
    "tweet_count": "33.3K Tweets"
  },
  {
    "name": "Tommaso",
    "query": "Tommaso",
    "rank": 10,
    "tweet_count": "3,140 Tweets"
  },
  {
    "name": "Serena",
    "query": "Serena",
    "rank": 11,
    "tweet_count": "14.3K Tweets"
  },
  {
    "name": "#AtalantaUdinese",
    "query": "#AtalantaUdinese",
    "rank": 12,
    "tweet_count": "1,533 Tweets"
  },
  {
    "name": "Flaza",
    "query": "Flaza",
    "rank": 13,
    "tweet_count": "2,383 Tweets"
  },
  {
    "name": "Pecco",
    "query": "Pecco",
    "rank": 14,
    "tweet_count": "3,802 Tweets"
  },
  {
    "name": "Dario",
    "query": "Dario",
    "rank": 15,
    "tweet_count": "8,403 Tweets"
  },
  {
    "name": "Raimondo",
    "query": "Raimondo",
    "rank": 16,
    "tweet_count": "2,015 Tweets"
  },
  {
    "name": "Gasperini",
    "query": "Gasperini",
    "rank": 17,
    "tweet_count": null
  },
  {
    "name": "Simeone",
    "query": "Simeone",
    "rank": 18,
    "tweet_count": "2,423 Tweets"
  },
  {
    "name": "Biraghi",
    "query": "Biraghi",
    "rank": 19,
    "tweet_count": null
  },
  {
    "name": "Sarri",
    "query": "Sarri",
    "rank": 20,
    "tweet_count": "2,349 Tweets"
  }
]
