[
  {
    "name": "#deprem",
    "query": "#deprem",
    "rank": 1,
    "tweet_count": "24K Tweets"
  },
  {
    "name": "#deprem",
    "query": "#deprem",
    "rank": 2,
    "tweet_count": "24K Tweets"
  },
  {
    "name": "#ErkenSeçim",
    "query": "#ErkenSeçim",
    "rank": 3,
    "tweet_count": "1,460 Tweets"
  },
  {
    "name": "Euro 12",
    "query": "\"Euro 12\"",
    "rank": 4,
    "tweet_count": "3,779 Tweets"
  },
  {
    "name": "milletittifakı afistiyoruz",
    "query": "\"milletittifakı afistiyoruz\"",
    "rank": 5,
    "tweet_count": null
  },
  {
    "name": "Ajanlar Türkiyede",
    "query": "\"Ajanlar Türkiyede\"",
    "rank": 6,
    "tweet_count": "1,591 Tweets"
  },
  {
    "name": "Dolar 11",
    "query": "\"Dolar 11\"",
    "rank": 7,
    "tweet_count": "23K Tweets"
  },
  {
    "name": "#Sakarya",
    "query": "#Sakarya",
    "rank": 8,
    "tweet_count": "1,005 Tweets"
  },
  {
    "name": "Marmara",
    "query": "Marmara",
    "rank": 9,
    "tweet_count": "1,853 Tweets"
  },
  {
    "name": "#CumhurİttifakıAFistiyoruz",
    "query": "#CumhurİttifakıAFistiyoruz",
    "rank": 10,
    "tweet_count": "15K Tweets"
  },
  {
    "name": "Kandilli Rasathanesi",
    "query": "\"Kandilli Rasathanesi\"",
    "rank": 11,
    "tweet_count": null
  },
  {
    "name": "KAÇTI",
    "query": "KAÇTI",
    "rank": 12,
    "tweet_count": "7,238 Tweets"
  },
  {
    "name": "Faiz",
    "query": "Faiz",
    "rank": 13,
    "tweet_count": "35.4K Tweets"
  },
  {
    "name": "Merkez Bankası",
    "query": "\"Merkez Bankası\"",
    "rank": 14,
    "tweet_count": "13K Tweets"
  },
  {
    "name": "Hissetmedim",
    "query": "Hissetmedim",
    "rank": 15,
    "tweet_count": "2,941 Tweets"
  },
  {
    "name": "Vahdettin",
    "query": "Vahdettin",
    "rank": 16,
    "tweet_count": "9,919 Tweets"
  },
  {
    "name": "Sürgün",
    "query": "Sürgün",
    "rank": 17,
    "tweet_count": "12.4K Tweets"
  },
  {
    "name": "Hissettim",
    "query": "Hissettim",
    "rank": 18,
    "tweet_count": "3,180 Tweets"
  },
  {
    "name": "Hepimize",
    "query": "Hepimize",
    "rank": 19,
    "tweet_count": "3,170 Tweets"
  },
  {
    "name": "Yoksulluk Bitiyor",
    "query": "\"Yoksulluk Bitiyor\"",
    "rank": 20,
    "tweet_count": null
  }
]
