[
  {
    "name": "#yegcc",
    "query": "#yegcc",
    "rank": 1,
    "tweet_count": "1,168 Tweets"
  },
  {
    "name": "Oilers",
    "query": "Oilers",
    "rank": 2,
    "tweet_count": "4,828 Tweets"
  },
  {
    "name": "#NintendoDirect",
    "query": "#NintendoDirect",
    "rank": 3,
    "tweet_count": "130K Tweets"
  },
  {
    "name": "Kirby",
    "query": "Kirby",
    "rank": 4,
    "tweet_count": "87.9K Tweets"
  },
  {
    "name": "Chrono Cross",
    "query": "\"Chrono Cross\"",
    "rank": 5,
    "tweet_count": "19.4K Tweets"
  },
  {
    "name": "Mario Strikers",
    "query": "\"Mario Strikers\"",
    "rank": 6,
    "tweet_count": "47.6K Tweets"
  },
  {
    "name": "Martin St-Louis",
    "query": "\"Martin St-Louis\"",
    "rank": 7,
    "tweet_count": "1,355 Tweets"
  },
  {
    "name": "Martin St-Louis",
    "query": "\"Martin St-Louis\"",
    "rank": 8,
    "tweet_count": "1,355 Tweets"
  },
  {
    "name": "Live A Live",
    "query": "\"Live A Live\"",
    "rank": 9,
    "tweet_count": "4,316 Tweets"
  },
  {
    "name": "Mario Kart",
    "query": "\"Mario Kart\"",
    "rank": 10,
    "tweet_count": "65.5K Tweets"
  },
  {
    "name": "Gazpacho",
    "query": "Gazpacho",
    "rank": 11,
    "tweet_count": "38.1K Tweets"
  },
  {
    "name": "Front Mission",
    "query": "\"Front Mission\"",
    "rank": 12,
    "tweet_count": "7,031 Tweets"
  },
  {
    "name": "Miis",
    "query": "Miis",
    "rank": 13,
    "tweet_count": "13.5K Tweets"
  },
  {
    "name": "Portal",
    "query": "Portal",
    "rank": 14,
    "tweet_count": "82.5K Tweets"
  },
  {
    "name": "Futurama",
    "query": "Futurama",
    "rank": 15,
    "tweet_count": "26.2K Tweets"
  },
  {
    "name": "Coconut Mall",
    "query": "\"Coconut Mall\"",
    "rank": 16,
    "tweet_count": "7,426 Tweets"
  },
  {
    "name": "Zelda",
    "query": "Zelda",
    "rank": 17,
    "tweet_count": "41.8K Tweets"
  },
  {
    "name": "No Man's Sky",
    "query": "\"No Man's Sky\"",
    "rank": 18,
    "tweet_count": "5,713 Tweets"
  },
  {
    "name": "Tuukka Rask",
    "query": "\"Tuukka Rask\"",
    "rank": 19,
    "tweet_count": "5,833 Tweets"
  },
  {
    "name": "Gorton",
    "query": "Gorton",
    "rank": 20,
    "tweet_count": "1,017 Tweets"
  }
]
