[
  {
    "name": "#5thNovWithBamBam",
    "query": "#5thNovWithBamBam",
    "rank": 1,
    "tweet_count": "15.1K Tweets"
  },
  {
    "name": "#เบื้องหลังลับลับกลัฟบุชเชอร์",
    "query": "#เบื้องหลังลับลับกลัฟบุชเชอร์",
    "rank": 2,
    "tweet_count": "84K Tweets"
  },
  {
    "name": "#CCWeekOfLovePeck_Friday",
    "query": "#CCWeekOfLovePeck_Friday",
    "rank": 3,
    "tweet_count": "23.9K Tweets"
  },
  {
    "name": "#ดีนะมีเฮียคนเดียว",
    "query": "#ดีนะมีเฮียคนเดียว",
    "rank": 4,
    "tweet_count": "17.8K Tweets"
  },
  {
    "name": "#คลับเฮ้าส์toxic",
    "query": "#คลับเฮ้าส์toxic",
    "rank": 5,
    "tweet_count": "112K Tweets"
  },
  {
    "name": "BUCHER X GULF KANAWUT",
    "query": "\"BUCHER X GULF KANAWUT\"",
    "rank": 6,
    "tweet_count": "69.3K Tweets"
  },
  {
    "name": "I VOTE",
    "query": "\"I VOTE\"",
    "rank": 7,
    "tweet_count": "1.76M Tweets"
  },
  {
    "name": "Worldwide Fans",
    "query": "\"Worldwide Fans\"",
    "rank": 8,
    "tweet_count": "2.38M Tweets"
  },
  {
    "name": "Choice TOP 10",
    "query": "\"Choice TOP 10\"",
    "rank": 9,
    "tweet_count": "2.04M Tweets"
  },
  {
    "name": "#TillTheEndOfTheMoon",
    "query": "#TillTheEndOfTheMoon",
    "rank": 10,
    "tweet_count": "4,864 Tweets"
  },
  {
    "name": "#ฟลุ้คณธัชแมสไหมล่ะ",
    "query": "#ฟลุ้คณธัชแมสไหมล่ะ",
    "rank": 11,
    "tweet_count": "5,756 Tweets"
  },
  {
    "name": "#มอร์นิ่ง702",
    "query": "#มอร์นิ่ง702",
    "rank": 12,
    "tweet_count": "16.1K Tweets"
  },
  {
    "name": "#treasure",
    "query": "#treasure",
    "rank": 13,
    "tweet_count": "1.7M Tweets"
  },
  {
    "name": "#straykids",
    "query": "#straykids",
    "rank": 14,
    "tweet_count": "2.71M Tweets"
  },
  {
    "name": "#mino",
    "query": "#mino",
    "rank": 15,
    "tweet_count": "42.3K Tweets"
  },
  {
    "name": "#astro",
    "query": "#astro",
    "rank": 16,
    "tweet_count": "434K Tweets"
  },
  {
    "name": "#MAMA2021",
    "query": "#MAMA2021",
    "rank": 17,
    "tweet_count": "388K Tweets"
  },
  {
    "name": "#enhypen",
    "query": "#enhypen",
    "rank": 18,
    "tweet_count": "2.29M Tweets"
  },
  {
    "name": "#ตลาดนัดtruz",
    "query": "#ตลาดนัดtruz",
    "rank": 19,
    "tweet_count": "1,575 Tweets"
  },
  {
    "name": "#MONSTAX",
    "query": "#MONSTAX",
    "rank": 20,
    "tweet_count": "192K Tweets"
  }
]
