[
  {
    "name": "Draymond",
    "query": "Draymond",
    "rank": 1,
    "tweet_count": "8,975 Tweets"
  },
  {
    "name": "#Warriors",
    "query": "#Warriors",
    "rank": 2,
    "tweet_count": "1,413 Tweets"
  },
  {
    "name": "#911LoneStar",
    "query": "#911LoneStar",
    "rank": 3,
    "tweet_count": "16.5K Tweets"
  },
  {
    "name": "Namjoon",
    "query": "Namjoon",
    "rank": 4,
    "tweet_count": "223K Tweets"
  },
  {
    "name": "#thecleaninglady",
    "query": "#thecleaninglady",
    "rank": 5,
    "tweet_count": "2,099 Tweets"
  },
  {
    "name": "Fitz",
    "query": "Fitz",
    "rank": 6,
    "tweet_count": "4,286 Tweets"
  },
  {
    "name": "Morbius",
    "query": "Morbius",
    "rank": 7,
    "tweet_count": "19.8K Tweets"
  },
  {
    "name": "Wiseman",
    "query": "Wiseman",
    "rank": 8,
    "tweet_count": "2,418 Tweets"
  },
  {
    "name": "Heat",
    "query": "Heat",
    "rank": 9,
    "tweet_count": "65.4K Tweets"
  },
  {
    "name": "Looney",
    "query": "Looney",
    "rank": 10,
    "tweet_count": "3,758 Tweets"
  },
  {
    "name": "Kuzma",
    "query": "Kuzma",
    "rank": 11,
    "tweet_count": "7,180 Tweets"
  },
  {
    "name": "MLB Network",
    "query": "\"MLB Network\"",
    "rank": 12,
    "tweet_count": "8,375 Tweets"
  },
  {
    "name": "#FantasyFootball",
    "query": "#FantasyFootball",
    "rank": 13,
    "tweet_count": "3,406 Tweets"
  },
  {
    "name": "Euphoria",
    "query": "Euphoria",
    "rank": 14,
    "tweet_count": "71.8K Tweets"
  },
  {
    "name": "Coachella",
    "query": "Coachella",
    "rank": 15,
    "tweet_count": "3,312 Tweets"
  },
  {
    "name": "Lashley",
    "query": "Lashley",
    "rank": 16,
    "tweet_count": "8,165 Tweets"
  },
  {
    "name": "#TrumpCrimeFamily",
    "query": "#TrumpCrimeFamily",
    "rank": 17,
    "tweet_count": "11.1K Tweets"
  },
  {
    "name": "Caleb Williams",
    "query": "\"Caleb Williams\"",
    "rank": 18,
    "tweet_count": "12.3K Tweets"
  },
  {
    "name": "Silicon Valley",
    "query": "\"Silicon Valley\"",
    "rank": 19,
    "tweet_count": "6,810 Tweets"
  }
]
