[
  {
    "name": "#กระเช้าสีดาEp15",
    "query": "#กระเช้าสีดาEp15",
    "rank": 1,
    "tweet_count": "43.9K Tweets"
  },
  {
    "name": "#JAYBonStationZ",
    "query": "#JAYBonStationZ",
    "rank": 2,
    "tweet_count": "32.2K Tweets"
  },
  {
    "name": "patrick cn music awards",
    "query": "\"patrick cn music awards\"",
    "rank": 3,
    "tweet_count": "229K Tweets"
  },
  {
    "name": "#PaiPai_东方风云榜",
    "query": "#PaiPai_东方风云榜",
    "rank": 4,
    "tweet_count": "224K Tweets"
  },
  {
    "name": "#bonnadol",
    "query": "#bonnadol",
    "rank": 5,
    "tweet_count": "15.5K Tweets"
  },
  {
    "name": "#สเปเชือกป่าน",
    "query": "#สเปเชือกป่าน",
    "rank": 6,
    "tweet_count": "63.2K Tweets"
  },
  {
    "name": "TeamNV 2Ys2gether",
    "query": "\"TeamNV 2Ys2gether\"",
    "rank": 7,
    "tweet_count": "12.7K Tweets"
  },
  {
    "name": "EXO-L",
    "query": "EXO-L",
    "rank": 8,
    "tweet_count": "25.4K Tweets"
  },
  {
    "name": "LIU YUXIN SOLO AWARD",
    "query": "\"LIU YUXIN SOLO AWARD\"",
    "rank": 9,
    "tweet_count": "9,878 Tweets"
  },
  {
    "name": "AMAs",
    "query": "AMAs",
    "rank": 10,
    "tweet_count": "487K Tweets"
  },
  {
    "name": "LGBTQ",
    "query": "LGBTQ",
    "rank": 11,
    "tweet_count": "95.6K Tweets"
  },
  {
    "name": "XiaoNai RedCarpet",
    "query": "\"XiaoNai RedCarpet\"",
    "rank": 12,
    "tweet_count": "62.8K Tweets"
  },
  {
    "name": "KEYU MUSIC AWARDS",
    "query": "\"KEYU MUSIC AWARDS\"",
    "rank": 13,
    "tweet_count": "9,603 Tweets"
  },
  {
    "name": "#เกมล่าทรชนep6",
    "query": "#เกมล่าทรชนep6",
    "rank": 14,
    "tweet_count": "13K Tweets"
  },
  {
    "name": "#JENO",
    "query": "#JENO",
    "rank": 15,
    "tweet_count": "151K Tweets"
  },
  {
    "name": "#GMMTVSafeHouseSS2D3",
    "query": "#GMMTVSafeHouseSS2D3",
    "rank": 16,
    "tweet_count": "201K Tweets"
  },
  {
    "name": "#SUHO",
    "query": "#SUHO",
    "rank": 17,
    "tweet_count": "22.2K Tweets"
  },
  {
    "name": "#สมรสเท่าเทียม",
    "query": "#สมรสเท่าเทียม",
    "rank": 18,
    "tweet_count": "410K Tweets"
  },
  {
    "name": "#แพทริค",
    "query": "#แพทริค",
    "rank": 19,
    "tweet_count": "319K Tweets"
  },
  {
    "name": "#วันบันเทิงTALKxริชชี่",
    "query": "#วันบันเทิงTALKxริชชี่",
    "rank": 20,
    "tweet_count": "9,107 Tweets"
  }
]
