[
  {
    "name": "#klimaatleiderschap",
    "query": "#klimaatleiderschap",
    "rank": 1,
    "tweet_count": "1,931 Tweets"
  },
  {
    "name": "Koeman",
    "query": "Koeman",
    "rank": 2,
    "tweet_count": "438K Tweets"
  },
  {
    "name": "#deepfake",
    "query": "#deepfake",
    "rank": 3,
    "tweet_count": null
  },
  {
    "name": "Onana",
    "query": "Onana",
    "rank": 4,
    "tweet_count": "2,013 Tweets"
  },
  {
    "name": "#coronamaatregelen",
    "query": "#coronamaatregelen",
    "rank": 5,
    "tweet_count": "9,279 Tweets"
  },
  {
    "name": "Xavi",
    "query": "Xavi",
    "rank": 6,
    "tweet_count": "203K Tweets"
  },
  {
    "name": "Frank de Grave",
    "query": "\"Frank de Grave\"",
    "rank": 7,
    "tweet_count": null
  },
  {
    "name": "#RayoBarça",
    "query": "#RayoBarça",
    "rank": 8,
    "tweet_count": "23.2K Tweets"
  },
  {
    "name": "Eneco",
    "query": "Eneco",
    "rank": 9,
    "tweet_count": null
  },
  {
    "name": "Biddinghuizen",
    "query": "Biddinghuizen",
    "rank": 10,
    "tweet_count": null
  },
  {
    "name": "Raisa",
    "query": "Raisa",
    "rank": 11,
    "tweet_count": "5,116 Tweets"
  },
  {
    "name": "Koevermans",
    "query": "Koevermans",
    "rank": 12,
    "tweet_count": null
  },
  {
    "name": "Raad van State",
    "query": "\"Raad van State\"",
    "rank": 13,
    "tweet_count": "1,137 Tweets"
  },
  {
    "name": "Donald Duck",
    "query": "\"Donald Duck\"",
    "rank": 14,
    "tweet_count": null
  },
  {
    "name": "Beste Mark Rutte",
    "query": "\"Beste Mark Rutte\"",
    "rank": 15,
    "tweet_count": null
  },
  {
    "name": "Pasveer",
    "query": "Pasveer",
    "rank": 16,
    "tweet_count": null
  },
  {
    "name": "Ab Osterhaus",
    "query": "\"Ab Osterhaus\"",
    "rank": 17,
    "tweet_count": "1,787 Tweets"
  },
  {
    "name": "Simple Minds",
    "query": "\"Simple Minds\"",
    "rank": 18,
    "tweet_count": null
  },
  {
    "name": "Hugo",
    "query": "Hugo",
    "rank": 19,
    "tweet_count": "49.9K Tweets"
  }
]
