[
  {
    "name": "Kante",
    "query": "Kante",
    "rank": 1,
    "tweet_count": "20.4K Tweets"
  },
  {
    "name": "Jota",
    "query": "Jota",
    "rank": 2,
    "tweet_count": "23.7K Tweets"
  },
  {
    "name": "#ForTheCulture",
    "query": "#ForTheCulture",
    "rank": 3,
    "tweet_count": null
  },
  {
    "name": "Havertz",
    "query": "Havertz",
    "rank": 4,
    "tweet_count": "33.1K Tweets"
  },
  {
    "name": "Kepa",
    "query": "Kepa",
    "rank": 5,
    "tweet_count": "260K Tweets"
  },
  {
    "name": "De Gea",
    "query": "\"De Gea\"",
    "rank": 6,
    "tweet_count": "14.8K Tweets"
  },
  {
    "name": "Lukaku",
    "query": "Lukaku",
    "rank": 7,
    "tweet_count": "55.6K Tweets"
  },
  {
    "name": "Mount",
    "query": "Mount",
    "rank": 8,
    "tweet_count": "96.7K Tweets"
  },
  {
    "name": "Diaz",
    "query": "Diaz",
    "rank": 9,
    "tweet_count": "95.7K Tweets"
  },
  {
    "name": "Kelleher",
    "query": "Kelleher",
    "rank": 10,
    "tweet_count": "43.1K Tweets"
  },
  {
    "name": "Chalobah",
    "query": "Chalobah",
    "rank": 11,
    "tweet_count": "13.7K Tweets"
  },
  {
    "name": "#LIVCHE",
    "query": "#LIVCHE",
    "rank": 12,
    "tweet_count": "12K Tweets"
  },
  {
    "name": "Matip",
    "query": "Matip",
    "rank": 13,
    "tweet_count": "13.6K Tweets"
  },
  {
    "name": "Kovacic",
    "query": "Kovacic",
    "rank": 14,
    "tweet_count": "7,808 Tweets"
  },
  {
    "name": "Alonso",
    "query": "Alonso",
    "rank": 15,
    "tweet_count": "28.5K Tweets"
  },
  {
    "name": "Klopp",
    "query": "Klopp",
    "rank": 16,
    "tweet_count": "36.3K Tweets"
  },
  {
    "name": "Mane",
    "query": "Mane",
    "rank": 17,
    "tweet_count": "62K Tweets"
  },
  {
    "name": "Thiago",
    "query": "Thiago",
    "rank": 18,
    "tweet_count": "83.1K Tweets"
  },
  {
    "name": "Reece",
    "query": "Reece",
    "rank": 19,
    "tweet_count": "15.2K Tweets"
  },
  {
    "name": "#PizzamanTwaNaDi",
    "query": "#PizzamanTwaNaDi",
    "rank": 20,
    "tweet_count": null
  }
]
