[
  {
    "name": "Jean Pyerre",
    "query": "\"Jean Pyerre\"",
    "rank": 1,
    "tweet_count": "2,034 Tweets"
  },
  {
    "name": "Big Juliette Brasil",
    "query": "\"Big Juliette Brasil\"",
    "rank": 2,
    "tweet_count": "11.1K Tweets"
  },
  {
    "name": "Datena",
    "query": "Datena",
    "rank": 3,
    "tweet_count": "1,412 Tweets"
  },
  {
    "name": "#EsporteNaBand",
    "query": "#EsporteNaBand",
    "rank": 4,
    "tweet_count": null
  },
  {
    "name": "HYUNA",
    "query": "HYUNA",
    "rank": 5,
    "tweet_count": "130K Tweets"
  },
  {
    "name": "#FoiGolpe",
    "query": "#FoiGolpe",
    "rank": 6,
    "tweet_count": "3,850 Tweets"
  },
  {
    "name": "#OClone",
    "query": "#OClone",
    "rank": 7,
    "tweet_count": "2,603 Tweets"
  },
  {
    "name": "#4EVER",
    "query": "#4EVER",
    "rank": 8,
    "tweet_count": "11.8K Tweets"
  },
  {
    "name": "Kayzer",
    "query": "Kayzer",
    "rank": 9,
    "tweet_count": "1,537 Tweets"
  },
  {
    "name": "BEN MENDES",
    "query": "\"BEN MENDES\"",
    "rank": 10,
    "tweet_count": null
  },
  {
    "name": "P창nico 6",
    "query": "\"P창nico 6\"",
    "rank": 11,
    "tweet_count": "1,997 Tweets"
  },
  {
    "name": "#CopaDoReiNaESPN",
    "query": "#CopaDoReiNaESPN",
    "rank": 12,
    "tweet_count": null
  },
  {
    "name": "Sidney",
    "query": "Sidney",
    "rank": 13,
    "tweet_count": "13.6K Tweets"
  },
  {
    "name": "BRIDGERTON SEASON 2 IS COMING",
    "query": "\"BRIDGERTON SEASON 2 IS COMING\"",
    "rank": 14,
    "tweet_count": "9,414 Tweets"
  },
  {
    "name": "Edwina",
    "query": "Edwina",
    "rank": 15,
    "tweet_count": "2,231 Tweets"
  },
  {
    "name": "billie",
    "query": "billie",
    "rank": 16,
    "tweet_count": "22.9K Tweets"
  },
  {
    "name": "Camar천es x Egito",
    "query": "\"Camar천es x Egito\"",
    "rank": 17,
    "tweet_count": null
  },
  {
    "name": "Gale",
    "query": "Gale",
    "rank": 18,
    "tweet_count": "8,544 Tweets"
  },
  {
    "name": "Kate",
    "query": "Kate",
    "rank": 19,
    "tweet_count": "49.7K Tweets"
  },
  {
    "name": "Francesca",
    "query": "Francesca",
    "rank": 20,
    "tweet_count": "23.5K Tweets"
  }
]
