[
  {
    "name": "#スカロケ",
    "query": "#スカロケ",
    "rank": 1,
    "tweet_count": "2,207 Tweets"
  },
  {
    "name": "#湊あくあ生放送",
    "query": "#湊あくあ生放送",
    "rank": 2,
    "tweet_count": "6,540 Tweets"
  },
  {
    "name": "真剣乱舞祭",
    "query": "真剣乱舞祭",
    "rank": 3,
    "tweet_count": "25.1K Tweets"
  },
  {
    "name": "#キラスタ",
    "query": "#キラスタ",
    "rank": 4,
    "tweet_count": null
  },
  {
    "name": "チョコ0個",
    "query": "チョコ0個",
    "rank": 5,
    "tweet_count": "13.5K Tweets"
  },
  {
    "name": "#LEOの遊び場",
    "query": "#LEOの遊び場",
    "rank": 6,
    "tweet_count": null
  },
  {
    "name": "#bayfmixp",
    "query": "#bayfmixp",
    "rank": 7,
    "tweet_count": null
  },
  {
    "name": "ドライフラワーの飾り",
    "query": "ドライフラワーの飾り",
    "rank": 8,
    "tweet_count": "3,202 Tweets"
  },
  {
    "name": "オンラインブース",
    "query": "オンラインブース",
    "rank": 9,
    "tweet_count": "1,158 Tweets"
  },
  {
    "name": "テディベアの飾り",
    "query": "テディベアの飾り",
    "rank": 10,
    "tweet_count": "2,700 Tweets"
  },
  {
    "name": "チョコの代わり",
    "query": "チョコの代わり",
    "rank": 11,
    "tweet_count": "28K Tweets"
  },
  {
    "name": "ペンラのteaser",
    "query": "ペンラのteaser",
    "rank": 12,
    "tweet_count": "3,008 Tweets"
  },
  {
    "name": "伊達ちゃん",
    "query": "伊達ちゃん",
    "rank": 13,
    "tweet_count": "1,247 Tweets"
  },
  {
    "name": "ブラックサンダー",
    "query": "ブラックサンダー",
    "rank": 14,
    "tweet_count": "13.3K Tweets"
  },
  {
    "name": "優待廃止",
    "query": "優待廃止",
    "rank": 15,
    "tweet_count": "3,330 Tweets"
  },
  {
    "name": "バレンタイン",
    "query": "バレンタイン",
    "rank": 16,
    "tweet_count": "2.82M Tweets"
  },
  {
    "name": "義理チョコ",
    "query": "義理チョコ",
    "rank": 17,
    "tweet_count": "64.9K Tweets"
  },
  {
    "name": "呪いチョコ",
    "query": "呪いチョコ",
    "rank": 18,
    "tweet_count": "6,730 Tweets"
  },
  {
    "name": "家族チョコ",
    "query": "家族チョコ",
    "rank": 19,
    "tweet_count": "13.4K Tweets"
  },
  {
    "name": "チョコの確率",
    "query": "チョコの確率",
    "rank": 20,
    "tweet_count": "11.7K Tweets"
  }
]
