[
  {
    "name": "#ATMMUN",
    "query": "#ATMMUN",
    "rank": 1,
    "tweet_count": "11.9K Tweets"
  },
  {
    "name": "#BUHARI𓃵",
    "query": "#BUHARI𓃵",
    "rank": 2,
    "tweet_count": "3,728 Tweets"
  },
  {
    "name": "Lindelof",
    "query": "Lindelof",
    "rank": 3,
    "tweet_count": "7,249 Tweets"
  },
  {
    "name": "#AskAGbaby",
    "query": "#AskAGbaby",
    "rank": 4,
    "tweet_count": null
  },
  {
    "name": "#TEKNOMUFASA",
    "query": "#TEKNOMUFASA",
    "rank": 5,
    "tweet_count": "1,265 Tweets"
  },
  {
    "name": "#MTNUduXDavido",
    "query": "#MTNUduXDavido",
    "rank": 6,
    "tweet_count": null
  },
  {
    "name": "Atletico",
    "query": "Atletico",
    "rank": 7,
    "tweet_count": "140K Tweets"
  },
  {
    "name": "Seyi Makinde",
    "query": "\"Seyi Makinde\"",
    "rank": 8,
    "tweet_count": "1,752 Tweets"
  },
  {
    "name": "Super Falcons",
    "query": "\"Super Falcons\"",
    "rank": 9,
    "tweet_count": "1,758 Tweets"
  },
  {
    "name": "Man United",
    "query": "\"Man United\"",
    "rank": 10,
    "tweet_count": "28.6K Tweets"
  },
  {
    "name": "Mandy",
    "query": "Mandy",
    "rank": 11,
    "tweet_count": "11.6K Tweets"
  },
  {
    "name": "Thomas Shelby",
    "query": "\"Thomas Shelby\"",
    "rank": 12,
    "tweet_count": "1,909 Tweets"
  },
  {
    "name": "Zamfara",
    "query": "Zamfara",
    "rank": 13,
    "tweet_count": "5,200 Tweets"
  },
  {
    "name": "Adeleke",
    "query": "Adeleke",
    "rank": 14,
    "tweet_count": "1,727 Tweets"
  },
  {
    "name": "Deputy Governor",
    "query": "\"Deputy Governor\"",
    "rank": 15,
    "tweet_count": "4,556 Tweets"
  },
  {
    "name": "Morocco",
    "query": "Morocco",
    "rank": 16,
    "tweet_count": "8,170 Tweets"
  },
  {
    "name": "Buchi",
    "query": "Buchi",
    "rank": 17,
    "tweet_count": "4,339 Tweets"
  },
  {
    "name": "Jonathan",
    "query": "Jonathan",
    "rank": 18,
    "tweet_count": "40.5K Tweets"
  },
  {
    "name": "McTominay",
    "query": "McTominay",
    "rank": 19,
    "tweet_count": "7,887 Tweets"
  }
]
