[
  {
    "name": "Hamilton",
    "query": "Hamilton",
    "rank": 1,
    "tweet_count": "22.6K Tweets"
  },
  {
    "name": "The NHL",
    "query": "\"The NHL\"",
    "rank": 2,
    "tweet_count": "14.3K Tweets"
  },
  {
    "name": "Nurse",
    "query": "Nurse",
    "rank": 3,
    "tweet_count": "58K Tweets"
  },
  {
    "name": "Hinshaw",
    "query": "Hinshaw",
    "rank": 4,
    "tweet_count": "2,452 Tweets"
  },
  {
    "name": "The Golden Girls",
    "query": "\"The Golden Girls\"",
    "rank": 5,
    "tweet_count": "83K Tweets"
  },
  {
    "name": "Happy New Year",
    "query": "\"Happy New Year\"",
    "rank": 6,
    "tweet_count": "1.69M Tweets"
  },
  {
    "name": "Mike Smith",
    "query": "\"Mike Smith\"",
    "rank": 7,
    "tweet_count": "2,371 Tweets"
  },
  {
    "name": "#Oilers",
    "query": "#Oilers",
    "rank": 8,
    "tweet_count": null
  },
  {
    "name": "#IndigoEvents",
    "query": "#IndigoEvents",
    "rank": 9,
    "tweet_count": null
  },
  {
    "name": "Bama",
    "query": "Bama",
    "rank": 10,
    "tweet_count": "32K Tweets"
  },
  {
    "name": "Keith Richards",
    "query": "\"Keith Richards\"",
    "rank": 11,
    "tweet_count": "1,330 Tweets"
  },
  {
    "name": "#legend",
    "query": "#legend",
    "rank": 12,
    "tweet_count": "4,601 Tweets"
  },
  {
    "name": "Tippett",
    "query": "Tippett",
    "rank": 13,
    "tweet_count": null
  },
  {
    "name": "McDavid",
    "query": "McDavid",
    "rank": 14,
    "tweet_count": "1,961 Tweets"
  },
  {
    "name": "Lake Placid",
    "query": "\"Lake Placid\"",
    "rank": 15,
    "tweet_count": "1,583 Tweets"
  },
  {
    "name": "100th Birthday",
    "query": "\"100th Birthday\"",
    "rank": 16,
    "tweet_count": "57.5K Tweets"
  },
  {
    "name": "Koskinen",
    "query": "Koskinen",
    "rank": 17,
    "tweet_count": null
  },
  {
    "name": "#EDMvsNJD",
    "query": "#EDMvsNJD",
    "rank": 18,
    "tweet_count": null
  },
  {
    "name": "McLeod",
    "query": "McLeod",
    "rank": 19,
    "tweet_count": "2,728 Tweets"
  },
  {
    "name": "Bonne Année",
    "query": "\"Bonne Année\"",
    "rank": 20,
    "tweet_count": "99.1K Tweets"
  }
]
