[
  {
    "name": "#lisa",
    "query": "#lisa",
    "rank": 1,
    "tweet_count": "680K Tweets"
  },
  {
    "name": "#おま1242",
    "query": "#おま1242",
    "rank": 2,
    "tweet_count": null
  },
  {
    "name": "#深澤辰哉",
    "query": "#深澤辰哉",
    "rank": 3,
    "tweet_count": "5,381 Tweets"
  },
  {
    "name": "Aゲート",
    "query": "Aゲート",
    "rank": 4,
    "tweet_count": null
  },
  {
    "name": "#ss954",
    "query": "#ss954",
    "rank": 5,
    "tweet_count": "1,181 Tweets"
  },
  {
    "name": "パーシヴァル",
    "query": "パーシヴァル",
    "rank": 6,
    "tweet_count": "1,869 Tweets"
  },
  {
    "name": "サンタナ",
    "query": "サンタナ",
    "rank": 7,
    "tweet_count": null
  },
  {
    "name": "メンヘラ型",
    "query": "メンヘラ型",
    "rank": 8,
    "tweet_count": null
  },
  {
    "name": "ウズベキスタン",
    "query": "ウズベキスタン",
    "rank": 9,
    "tweet_count": "5,696 Tweets"
  },
  {
    "name": "音ゲーマー",
    "query": "音ゲーマー",
    "rank": 10,
    "tweet_count": "1,592 Tweets"
  },
  {
    "name": "マヨちゃん",
    "query": "マヨちゃん",
    "rank": 11,
    "tweet_count": null
  },
  {
    "name": "A・J・コール",
    "query": "A・J・コール",
    "rank": 12,
    "tweet_count": "1,021 Tweets"
  },
  {
    "name": "正力松太郎賞",
    "query": "正力松太郎賞",
    "rank": 13,
    "tweet_count": null
  },
  {
    "name": "天下五剣",
    "query": "天下五剣",
    "rank": 14,
    "tweet_count": null
  },
  {
    "name": "IDOLiSH7",
    "query": "IDOLiSH7",
    "rank": 15,
    "tweet_count": "33.7K Tweets"
  },
  {
    "name": "オフショア債利払い",
    "query": "オフショア債利払い",
    "rank": 16,
    "tweet_count": "1,434 Tweets"
  },
  {
    "name": "これ100回",
    "query": "これ100回",
    "rank": 17,
    "tweet_count": "1,026 Tweets"
  },
  {
    "name": "猶予期間終了",
    "query": "猶予期間終了",
    "rank": 18,
    "tweet_count": "1,329 Tweets"
  },
  {
    "name": "マルタさん",
    "query": "マルタさん",
    "rank": 19,
    "tweet_count": "6,867 Tweets"
  }
]
